[
  {
    "fechaNacimiento": "24 nov. 2021 06:36:46",
    "tipoSangre": "B-",
    "nacionalidad": "Costarricense",
    "lugarResidencia": "Heredia",
    "numerosTelefonicos": [],
    "vacunasAplicadas": [
      {
        "fechaAplicacion": "24 nov. 2021 06:37:52",
        "nombreVacuna": "COVID",
        "farmaceutica": "Pfizer",
        "numLote": 1
      }
    ],
    "historial": "Se ha registrado al paciente en el sistema. Fecha:2021-11-24\nSe ha asignado la cita ID: 2 a nombre del funcionario de medicina Eduardo Mendez Fecha: 2021-11-24Se ha atendido la cita ID: 1 a nombre del funcionario de medicina Eduardo Mendez Fecha: 2021-11-24",
    "citas": [
      {
        "especialidad": "Administrativa",
        "fechaCita": "12 dic. 2021 00:00:00",
        "comentario": "Holaaaaaaaaaa",
        "hora": 7,
        "identificador": 1,
        "estadoCita": "Realizada",
        "bitacora": "Se ha registrado la cita\nFecha: 2021-11-24T06:37:55.939634Se ha atendido la cita a nombre del funcionario de medicina Eduardo Mendez\n",
        "diagnosticos": [
          {
            "nombre": "Calentura",
            "nivel": "Leve",
            "tratamientos": [
              {
                "nombre": "Pastillas",
                "dosis": 1,
                "tipo": "Medicamento"
              }
            ]
          }
        ]
      },
      {
        "especialidad": "Administrativa",
        "fechaCita": "1 ene. 2020 00:00:00",
        "comentario": "Holaaaaaa2",
        "hora": 9,
        "identificador": 2,
        "estadoCita": "Asignada",
        "bitacora": "Se ha registrado la cita\nFecha: 2021-11-24T06:37:20.612551600Se ha asignado la cita a nombre del funcionario de medicina Eduardo Mendez\n",
        "diagnosticos": []
      }
    ],
    "diagnosticos": [],
    "tratamientos": [],
    "hospitalizaciones": [
      {
        "fechaInicio": "24 nov. 2021 06:37:54",
        "centroAtencion": {
          "codigo": 1,
          "capacidadPacientes": 125,
          "nombre": "Hospital TEC",
          "lugarUbicacion": "Cartago",
          "tipo": "Hospital",
          "funcionarios": []
        },
        "funcionarioMedicina": {
          "codigoMedico": 1,
          "especialidades": [],
          "tipo": "Doctor",
          "fechaIngreso": "24 nov. 2021 06:36:46",
          "usuario": "drMendez",
          "contrasenha": "123",
          "cedula": "4578123565",
          "nombre": "Eduardo Mendez"
        },
        "diagnosticos": [
          {
            "nombre": "Calentura",
            "nivel": "Leve",
            "tratamientos": [
              {
                "nombre": "Pastillas",
                "dosis": 1,
                "tipo": "Medicamento"
              }
            ]
          }
        ],
        "especialidad": "Administrativa",
        "estado": "Hospitalizado."
      }
    ],
    "usuario": "mreveiz",
    "contrasenha": "123",
    "cedula": "117680133",
    "nombre": "Marco Reveiz"
  }
]